LICENSE
README.md
pyproject.toml
pycns/__init__.py
pycns.egg-info/PKG-INFO
pycns.egg-info/SOURCES.txt
pycns.egg-info/dependency_links.txt
pycns.egg-info/requires.txt
pycns.egg-info/top_level.txt